Assets/__init__.py
legendarycli/__init__.py
legendarycli-0.0.8.dist-info/LICENSE.txt
legendarycli-0.0.8.dist-info/METADATA
legendarycli-0.0.8.dist-info/WHEEL
legendarycli-0.0.8.dist-info/entry_points.txt
legendarycli-0.0.8.dist-info/top_level.txt
legendarycli-0.0.8.dist-info/RECORD
